{
  "generatedAt": "2026-03-12T15:32:44.771Z",
  "count": 7,
  "files": [
    {
      "name": "american boy - disco.mid",
      "displayName": "american boy - disco",
      "size": "1.7 KB",
      "sizeBytes": 1765,
      "modified": "2026-03-12T15:32:44.120Z"
    },
    {
      "name": "Do i do Bass.mid",
      "displayName": "Do i do Bass",
      "size": "13.8 KB",
      "sizeBytes": 14105,
      "modified": "2026-03-12T15:32:44.119Z"
    },
    {
      "name": "Lavender Haze  Taylor Swift Funk Cover  Strutman Lane [bass].mid",
      "displayName": "Lavender Haze Taylor Swift Funk Cover Strutman Lane",
      "size": "4.3 KB",
      "sizeBytes": 4401,
      "modified": "2026-03-12T15:32:44.120Z"
    },
    {
      "name": "Maroon 5 - Wait (Chromeo Remix) (Audio) [bass].mid",
      "displayName": "Maroon 5 - Wait (Chromeo Remix) (Audio)",
      "size": "6.9 KB",
      "sizeBytes": 7113,
      "modified": "2026-03-12T15:32:44.120Z"
    },
    {
      "name": "Obsessed.mid",
      "displayName": "Obsessed",
      "size": "7.4 KB",
      "sizeBytes": 7564,
      "modified": "2026-03-12T15:32:44.120Z"
    },
    {
      "name": "Show Me How.mid",
      "displayName": "Show Me How",
      "size": "10.6 KB",
      "sizeBytes": 10808,
      "modified": "2026-03-12T15:32:44.120Z"
    },
    {
      "name": "Up Top - Busty and the bass.mid",
      "displayName": "Up Top - Busty and the bass",
      "size": "17.7 KB",
      "sizeBytes": 18130,
      "modified": "2026-03-12T15:32:44.120Z"
    }
  ]
}